tikz/__init__.py
tikz/tikz.py
tikz-0.0.10.dist-info/LICENSE.txt
tikz-0.0.10.dist-info/METADATA
tikz-0.0.10.dist-info/WHEEL
tikz-0.0.10.dist-info/top_level.txt
tikz-0.0.10.dist-info/RECORD
