Metadata-Version: 2.1
Name: tikz
Version: 0.0.10
Summary: TikZ Figure Generator
Home-page: https://gitlab.com/davidwoodburn/tikz
Author: David Woodburn
Author-email: david.woodburn@icloud.com
Classifier: Programming Language :: Python :: 3
Classifier: License :: OSI Approved :: MIT License
Classifier: Operating System :: OS Independent
Requires-Python: >=3.6
License-File: LICENSE.txt
Requires-Dist: numpy
